cryptoshred/__init__.py
cryptoshred/app/__init__.py
cryptoshred/app/business/__init__.py
cryptoshred/app/business/cli.py
cryptoshred/app/business/decrypt.py
cryptoshred/app/business/encrypt.py
cryptoshred/app/business/map.py
cryptoshred/app/ui/__init__.py
cryptoshred/app/ui/cli.py
cryptoshred/app/ui/decrypt.py
cryptoshred/app/ui/encrypt.py
cryptoshred/app/ui/map.py
cryptoshred/asynchronous/__init__.py
cryptoshred/asynchronous/convenience.py
cryptoshred/backends.py
cryptoshred/config.py
cryptoshred/convenience.py
cryptoshred/engines.py
cryptoshred/entities.py
cryptoshred/exceptions.py
cryptoshred-0.0.7.dist-info/entry_points.txt
cryptoshred-0.0.7.dist-info/LICENSE
cryptoshred-0.0.7.dist-info/WHEEL
cryptoshred-0.0.7.dist-info/METADATA
cryptoshred-0.0.7.dist-info/RECORD
